{
  "url": "https://library.educause.edu/topics/infrastructure-and-research-technologies/artificial-intelligence-ai",
  "final_url": "https://library.educause.edu/topics/infrastructure-and-research-technologies/artificial-intelligence-ai",
  "retrieved_at": "2026-01-22T00:14:09.372967Z",
  "http_status": 200,
  "title": "Artificial Intelligence (AI) | EDUCAUSE Library",
  "site_name": "library.educause.edu",
  "content_type": "text/html",
  "headings": [
    {
      "level": "h2",
      "text": "Featured Showcase"
    },
    {
      "level": "h2",
      "text": "Upcoming Showcase"
    },
    {
      "level": "h2",
      "text": "Past Showcases"
    },
    {
      "level": "h2",
      "text": "Focus Areas"
    },
    {
      "level": "h2",
      "text": "Library Topics"
    },
    {
      "level": "h2",
      "text": "Research"
    },
    {
      "level": "h2",
      "text": "Publications"
    },
    {
      "level": "h2",
      "text": "Benchmarking and Assessment"
    },
    {
      "level": "h2",
      "text": "Upcoming Events"
    },
    {
      "level": "h2",
      "text": "Signature Conferences"
    },
    {
      "level": "h2",
      "text": "Career Advancement Guides"
    },
    {
      "level": "h2",
      "text": "Annual Conference"
    },
    {
      "level": "h2",
      "text": "Leadership & Management Programs"
    },
    {
      "level": "h2",
      "text": "More Learning Experiences"
    },
    {
      "level": "h2",
      "text": "Get Connected"
    },
    {
      "level": "h2",
      "text": "Volunteer"
    },
    {
      "level": "h2",
      "text": "Career Center"
    },
    {
      "level": "h2",
      "text": "Awards"
    },
    {
      "level": "h2",
      "text": "My EDUCAUSE Profile"
    },
    {
      "level": "h2",
      "text": "About Us"
    },
    {
      "level": "h2",
      "text": "Careers at EDUCAUSE"
    },
    {
      "level": "h2",
      "text": "Membership"
    },
    {
      "level": "h2",
      "text": "Corporate Engagement"
    },
    {
      "level": "h1",
      "text": "Artificial Intelligence (AI)"
    },
    {
      "level": "h2",
      "text": "Sort by:"
    },
    {
      "level": "h2",
      "text": "Filter your results:"
    }
  ],
  "full_text": "Artificial Intelligence (AI)\nRecent Spotlight\n-\n-\nThree Years In: Reflections and Considerations for the Next Chapter of AI in Higher Education\nArtificial intelligence has the potential to transform higher education by connecting student experiences, improving operations, and enhancing outcomes. But unlocking its full potential will require better data integration, deeper cross-campus collaboration, well-defined ROI measures, increased environmental transparency, and more nuanced conversations about its role.",
  "excerpt": "Artificial Intelligence (AI) Recent Spotlight - - Three Years In: Reflections and Considerations for the Next Chapter of AI in Higher Education Artificial intelligence has the potential to transform higher education by connecting student experiences, improving operations, and enhancing outcomes. But unlocking its full potential will require better data integration, deeper cross-campus collaboration, well-defined ROI measures, increased environmental transparency, and more nuanced conversations about its role.",
  "word_count": 66,
  "content_hash": "7c9c101f23f10f4fd55c62c17a21a118a546db2de401ec760afa9d5ad64e4053",
  "scrape_status": "success",
  "blocked_reason": null,
  "notes": {
    "section": "AI Basics",
    "source_type": "University / Official",
    "relevance_note": "Higher-education focused overview of artificial intelligence, including institutional context and implications.",
    "date_added": "2026-01-21",
    "url": "https://library.educause.edu/topics/infrastructure-and-research-technologies/artificial-intelligence-ai"
  }
}